{
  "fetched_at": "2026-07-19T07:18:38.400991+00:00",
  "stories": [
    {
      "title": "I built a browser-based P2P file transfer tool using WebRTC",
      "url": "https://airdows.com/",
      "summary": "<p>Article URL: <a href=\"https://airdows.com/\">https://airdows.com/</a></p>\n<p>Comments URL: <a href=\"https://news.ycombinator.com/item?id=48964424\">https://news.ycombinator.com/item?id=48964424</a></p>\n<p>Points: 14</p>\n<p># Comments: 10</p>",
      "published": "Sun, 19 Jul 2026 02:17:03 +0000",
      "source": "Hacker News"
    },
    {
      "title": "AI Mania Is Eviscerating Global Decision-Making",
      "url": "https://ludic.mataroa.blog/blog/ai-mania-is-eviscerating-global-decision-making/#fnref:3",
      "summary": "<p>Article URL: <a href=\"https://ludic.mataroa.blog/blog/ai-mania-is-eviscerating-global-decision-making/#fnref:3\">https://ludic.mataroa.blog/blog/ai-mania-is-eviscerating-global-decision-making/#fnref:3</a></p>\n<p>Comments URL: <a href=\"https://news.ycombinator.com/item?id=48964185\">https://news.yc",
      "published": "Sun, 19 Jul 2026 01:29:19 +0000",
      "source": "Hacker News"
    },
    {
      "title": "Transcribe.cpp",
      "url": "https://workshop.cjpais.com/projects/transcribe-cpp",
      "summary": "<p>Article URL: <a href=\"https://workshop.cjpais.com/projects/transcribe-cpp\">https://workshop.cjpais.com/projects/transcribe-cpp</a></p>\n<p>Comments URL: <a href=\"https://news.ycombinator.com/item?id=48963879\">https://news.ycombinator.com/item?id=48963879</a></p>\n<p>Points: 380</p>\n<p># Comments: 6",
      "published": "Sun, 19 Jul 2026 00:38:26 +0000",
      "source": "Hacker News"
    },
    {
      "title": "Mayor Mamdani Says Landlords Can't Use AI Images to Advertise",
      "url": "https://petapixel.com/2026/07/16/mayor-mamdani-says-landlords-cant-secretly-use-ai-images-to-advertise-properties/",
      "summary": "<p>Article URL: <a href=\"https://petapixel.com/2026/07/16/mayor-mamdani-says-landlords-cant-secretly-use-ai-images-to-advertise-properties/\">https://petapixel.com/2026/07/16/mayor-mamdani-says-landlords-cant-secretly-use-ai-images-to-advertise-properties/</a></p>\n<p>Comments URL: <a href=\"https://ne",
      "published": "Sat, 18 Jul 2026 22:13:39 +0000",
      "source": "Hacker News"
    },
    {
      "title": "Goodbye, and Thanks for All the Bikesheds",
      "url": "https://queue.acm.org/detail.cfm?id=3818307",
      "summary": "<p>Article URL: <a href=\"https://queue.acm.org/detail.cfm?id=3818307\">https://queue.acm.org/detail.cfm?id=3818307</a></p>\n<p>Comments URL: <a href=\"https://news.ycombinator.com/item?id=48960155\">https://news.ycombinator.com/item?id=48960155</a></p>\n<p>Points: 203</p>\n<p># Comments: 204</p>",
      "published": "Sat, 18 Jul 2026 17:27:24 +0000",
      "source": "Hacker News"
    }
  ]
}